{
    "ObjArchives": [
        {
            "archive": "archive.0/_219775_archive_1.a",
            "objects": [
                [
                    "reYIK_d.o",
                    43000
                ],
                [
                    "w53B8_d.o",
                    11900
                ],
                [
                    "FiHPh_d.o",
                    12182
                ],
                [
                    "QRQns_d.o",
                    14844
                ],
                [
                    "a3M3m_d.o",
                    10756
                ],
                [
                    "gKx0G_d.o",
                    10490
                ],
                [
                    "IWW0i_d.o",
                    9068
                ],
                [
                    "CrgaQ_d.o",
                    433532
                ],
                [
                    "amcQwB.o",
                    124830
                ]
            ],
            "size": 670602
        }
    ],
    "Modules": {
        "dff": {
            "start_perf": [
                0.31357312202453613,
                0.088965000000000002,
                0.047501000000000002,
                313428,
                385704,
                1735541132.6676271,
                2305329458558847
            ],
            "nMops": 116,
            "child_modules": {},
            "Compiled": "Yes",
            "nRouts": 18,
            "Compiled Times": 1,
            "end_perf": [
                0.31504511833190918,
                0.090436000000000002,
                0.047501000000000002,
                313428,
                385704,
                2305329463909028,
                34359738369,
                0
            ],
            "nQuads": 61
        },
        "adc_top_tb": {
            "start_perf": [
                0.31506705284118652,
                0.090458999999999998,
                0.047501000000000002,
                313428,
                385704,
                1735541132.669121,
                2305329463958310
            ],
            "significant_routs": [
                [
                    1,
                    "R_VCSgd_CrgaQ_1",
                    9410982,
                    12224,
                    2464
                ],
                [
                    130,
                    "R_VCSgd_CrgaQ_82",
                    14112415,
                    20943,
                    3874
                ]
            ],
            "child_modules": {},
            "nMops": 30872,
            "Compiled": "Yes",
            "nRouts": 788,
            "Compiled Times": 1,
            "end_perf": [
                0.39885711669921875,
                0.171602,
                0.050143,
                314524,
                385704,
                2305329766480324,
                42949672961,
                0
            ],
            "nQuads": 9635
        },
        "...MASTER...": {
            "start_perf": [
                0.29421210289001465,
                0.077420000000000003,
                0.039685999999999999,
                311484,
                385704,
                1735541132.6482661,
                2305329388686514
            ],
            "nMops": 23,
            "child_modules": {
                "sp_ram": 1,
                "adc_top_tb": 1,
                "dff": 1,
                "std": 1,
                "true_dp_ram": 1,
                "dff_rs": 1,
                "simple_dp_ram": 1,
                "dff_rs_ld": 1
            },
            "end_perf": [
                0.2961280345916748,
                0.077476000000000003,
                0.041544999999999999,
                312464,
                385704,
                2305329395631698,
                0,
                0
            ],
            "nQuads": 12,
            "nRouts": 16
        },
        "std": {
            "start_perf": [
                0.29618310928344727,
                0.077512999999999999,
                0.041564999999999998,
                312464,
                385704,
                1735541132.6502371,
                2305329395799018
            ],
            "child_modules": {},
            "svclass": [
                "$vcs_nba_dyn_obj",
                576,
                35,
                2,
                2,
                0,
                "sigprop$$",
                576,
                35,
                2,
                2,
                0,
                "process",
                2380,
                200,
                8,
                8,
                0,
                "event",
                597,
                34,
                2,
                2,
                0,
                "mailbox",
                1769,
                140,
                9,
                9,
                0,
                "semaphore",
                1119,
                84,
                5,
                5,
                0
            ],
            "nMops": 528,
            "Compiled": "Yes",
            "nRouts": 33,
            "Compiled Times": 1,
            "end_perf": [
                0.30042004585266113,
                0.079592999999999997,
                0.043720000000000002,
                313428,
                385704,
                2305329411137295,
                8589934594,
                0
            ],
            "nQuads": 218
        },
        "true_dp_ram": {
            "start_perf": [
                0.30600690841674805,
                0.081410999999999997,
                0.047489000000000003,
                313428,
                385704,
                1735541132.6600609,
                2305329431253039
            ],
            "nMops": 595,
            "child_modules": {},
            "Compiled": "Yes",
            "nRouts": 44,
            "Compiled Times": 1,
            "end_perf": [
                0.30927491188049316,
                0.084678000000000003,
                0.047489000000000003,
                313428,
                385704,
                2305329443093954,
                21474836481,
                0
            ],
            "nQuads": 279
        },
        "sp_ram": {
            "start_perf": [
                0.30045199394226074,
                0.079614000000000004,
                0.043730999999999999,
                313428,
                385704,
                1735541132.654506,
                2305329411196841
            ],
            "nMops": 327,
            "child_modules": {},
            "Compiled": "Yes",
            "nRouts": 30,
            "Compiled Times": 1,
            "end_perf": [
                0.30338501930236816,
                0.080050999999999997,
                0.046226999999999997,
                313428,
                385704,
                2305329421842872,
                12884901889,
                0
            ],
            "nQuads": 161
        },
        "simple_dp_ram": {
            "start_perf": [
                0.30341410636901855,
                0.080070000000000002,
                0.046237,
                313428,
                385704,
                1735541132.6574681,
                2305329421888194
            ],
            "nMops": 328,
            "child_modules": {},
            "Compiled": "Yes",
            "nRouts": 33,
            "Compiled Times": 1,
            "end_perf": [
                0.30597591400146484,
                0.081391000000000005,
                0.047477999999999999,
                313428,
                385704,
                2305329431201027,
                17179869185,
                0
            ],
            "nQuads": 171
        },
        "dff_rs_ld": {
            "start_perf": [
                0.30930209159851074,
                0.084706000000000004,
                0.047489000000000003,
                313428,
                385704,
                1735541132.6633561,
                2305329443140992
            ],
            "nMops": 227,
            "child_modules": {},
            "Compiled": "Yes",
            "nRouts": 26,
            "Compiled Times": 1,
            "end_perf": [
                0.31166601181030273,
                0.087068000000000006,
                0.047490999999999998,
                313428,
                385704,
                2305329451730549,
                25769803777,
                0
            ],
            "nQuads": 116
        },
        "dff_rs": {
            "start_perf": [
                0.31169390678405762,
                0.087085999999999997,
                0.047501000000000002,
                313428,
                385704,
                1735541132.6657479,
                2305329451776121
            ],
            "nMops": 208,
            "child_modules": {},
            "Compiled": "Yes",
            "nRouts": 25,
            "Compiled Times": 1,
            "end_perf": [
                0.31354713439941406,
                0.088939000000000004,
                0.047501000000000002,
                313428,
                385704,
                2305329458513305,
                30064771073,
                0
            ],
            "nQuads": 105
        }
    },
    "CompUnits": {
        "amcQw_d": {
            "mod": "...MASTER...",
            "text": 839,
            "bytes": 9942,
            "out": "objs/amcQw_d.o",
            "mode": 4,
            "checksum": 0
        },
        "FiHPh_d": {
            "mod": "simple_dp_ram",
            "text": 2741,
            "bytes": 12182,
            "out": "FiHPh_d.o",
            "mode": 4,
            "checksum": 0,
            "archive": "archive.0/_219775_archive_1.a"
        },
        "a3M3m_d": {
            "mod": "dff_rs_ld",
            "text": 2247,
            "bytes": 10756,
            "out": "a3M3m_d.o",
            "mode": 4,
            "checksum": 0,
            "archive": "archive.0/_219775_archive_1.a"
        },
        "CrgaQ_d": {
            "mod": "adc_top_tb",
            "text": 294904,
            "bytes": 433532,
            "out": "CrgaQ_d.o",
            "mode": 4,
            "checksum": 0,
            "archive": "archive.0/_219775_archive_1.a"
        },
        "reYIK_d": {
            "mod": "std",
            "text": 7325,
            "bytes": 43000,
            "out": "reYIK_d.o",
            "checksum": 0,
            "cls": 7017,
            "mode": 4,
            "archive": "archive.0/_219775_archive_1.a"
        },
        "QRQns_d": {
            "mod": "true_dp_ram",
            "text": 4647,
            "bytes": 14844,
            "out": "QRQns_d.o",
            "mode": 4,
            "checksum": 0,
            "archive": "archive.0/_219775_archive_1.a"
        },
        "w53B8_d": {
            "mod": "sp_ram",
            "text": 2717,
            "bytes": 11900,
            "out": "w53B8_d.o",
            "mode": 4,
            "checksum": 0,
            "archive": "archive.0/_219775_archive_1.a"
        },
        "gKx0G_d": {
            "mod": "dff_rs",
            "text": 2107,
            "bytes": 10490,
            "out": "gKx0G_d.o",
            "mode": 4,
            "checksum": 0,
            "archive": "archive.0/_219775_archive_1.a"
        },
        "IWW0i_d": {
            "mod": "dff",
            "text": 1211,
            "bytes": 9068,
            "out": "IWW0i_d.o",
            "mode": 4,
            "checksum": 0,
            "archive": "archive.0/_219775_archive_1.a"
        }
    },
    "reusePaths": {},
    "stat": {
        "ru_self_end": {
            "ru_majflt": 0,
            "ru_utime_sec": 0.172989,
            "ru_nvcsw": 48,
            "ru_stime_sec": 0.051338000000000002,
            "ru_nivcsw": 6,
            "ru_maxrss_kb": 132428,
            "ru_minflt": 16420
        },
        "ru_childs_end": {
            "ru_majflt": 0,
            "ru_utime_sec": 0.024719000000000001,
            "ru_nvcsw": 44,
            "ru_stime_sec": 0.033702999999999997,
            "ru_nivcsw": 5,
            "ru_maxrss_kb": 117348,
            "ru_minflt": 14656
        },
        "peak_mem_kb": 385704,
        "cpu_cycles_end": 2305329775692713
    }
}